LICENSE
MANIFEST.in
README.rst
requirements.txt
setup.cfg
setup.py
authorized/__init__.py
authorized/admin.py
authorized/api_check.py
authorized/api_request.py
authorized/api_token.py
authorized/api_utils.py
authorized/apps.py
authorized/middleware.py
authorized/models.py
authorized/serializers.py
authorized/urls.py
authorized/views.py
authorized/migrations/0001_create_authorized_applications_table.py
authorized/migrations/__init__.py
authorized/tests/__init__.py
authorized/tests/test_api_requests.py
authorized/tests/test_api_token.py
authorized/tests/test_middleware.py
django_api_middleware.egg-info/PKG-INFO
django_api_middleware.egg-info/SOURCES.txt
django_api_middleware.egg-info/dependency_links.txt
django_api_middleware.egg-info/requires.txt
django_api_middleware.egg-info/top_level.txt